{
  "counters": {
    "ideas_created": 15,
    "voice_recordings": 0,
    "tasks_completed": 32,
    "focus_sessions": 11,
    "focus_total_minutes": 455,
    "perfect_focus_days": 0,
    "one_time_tasks_completed": 0,
    "max_journal_streak": 11,
    "max_focus_streak": 8,
    "daily_task_completions": {
      "task_1758204789679_n1jb2j": {
        "count": 6,
        "task_name": "VibeCoding實作與優化",
        "project": "project_1758071019675_m6ec2d"
      },
      "task_1758115807755_a1wr4p": {
        "count": 4,
        "task_name": "肌力訓練",
        "project": "project_1758034079337_fsocau"
      },
      "task_1758115789184_jz9oj7": {
        "count": 6,
        "task_name": "運動8000步",
        "project": "project_1758034079337_fsocau"
      },
      "task_1758087008303_4nvv3h": {
        "count": 1,
        "task_name": "創意原點：用心智圖探索與連結新點子",
        "project": "project_1758036096750_gcncrc"
      },
      "task_1758087008303_kpxdik": {
        "count": 1,
        "task_name": "韌性寫作：透過日誌反思來整合並分享觀點",
        "project": "project_1758036096750_gcncrc"
      },
      "task_1758087008302_skpi4j": {
        "count": 4,
        "task_name": "閱讀與分析：整理書中觀點並建立筆記框架",
        "project": "project_1758036096750_gcncrc"
      },
      "task_1758086746197_q5k6nv": {
        "count": 3,
        "task_name": "AI 技術探索",
        "project": "project_1758036096750_gcncrc"
      }
    }
  },
  "achievements_unlocked": [
    {
      "id": "ideas_10",
      "name": "思想的起點",
      "tier": "common",
      "unlocked_at": "2025-10-01T03:55:12.407Z"
    },
    {
      "id": "journal_streak_7",
      "name": "自省的習慣",
      "tier": "uncommon",
      "unlocked_at": "2025-10-01T03:55:12.407Z"
    },
    {
      "id": "focus_streak_7",
      "name": "專注修行者",
      "tier": "uncommon",
      "unlocked_at": "2025-10-01T03:55:12.407Z"
    }
  ]
}